django_aid/__init__.py
django_aid/django/__init__.py
django_aid/django/jinja2.py
django_aid/django/middleware.py
django_aid/django/model.py
django_aid/drf/__init__.py
django_aid/drf/drf_yasg.py
django_aid/drf/exceptions.py
django_aid/drf/renderers.py
django_aid/drf/viewsets.py
django_aid/drf/fields/__init__.py
django_aid/drf/fields/pk_model_field.py
django_aid-0.1.10.dist-info/LICENSE
django_aid-0.1.10.dist-info/METADATA
django_aid-0.1.10.dist-info/WHEEL
django_aid-0.1.10.dist-info/top_level.txt
django_aid-0.1.10.dist-info/zip-safe
django_aid-0.1.10.dist-info/RECORD
