Metadata-Version: 2.1
Name: django-aid
Version: 0.1.10
Summary: Helper module used in general django applications
Home-page: https://github.com/LeeHanYeong/django-aid
Author: lhy
Author-email: dev@lhy.kr
License: MIT
Platform: UNKNOWN
Classifier: Framework :: Django
Classifier: Programming Language :: Python
Classifier: Programming Language :: Python :: 3.7
Classifier: Programming Language :: Python :: 3.8
Requires-Python: >=3.7
Requires-Dist: django
Requires-Dist: djangorestframework
Requires-Dist: drf-yasg
